{"cameraMode":{"drawMode":0,"name":"Shaded","section":"Shading Mode"},"sceneLighting":true,"audioPlay":false,"sceneViewState":{"m_AlwaysRefresh":false,"showFog":true,"showSkybox":true,"showFlares":true,"showImageEffects":true,"showParticleSystems":true,"showVisualEffectGraphs":true,"m_FxEnabled":true},"in2DMode":false,"pivot":{"x":363.7077331542969,"y":193.50852966308595,"z":0.4967701733112335},"rotation":{"x":-0.03179444372653961,"y":-0.007235520053654909,"z":0.00022223623818717897,"w":-0.999496340751648},"size":97.44711303710938,"orthographic":false}